{
  "_fv": 79,
  "_type": "procedure",
  "definition": {
    "procedurexml": "<xml xmlns=\"https://developers.google.com/blockly/xml\"><variables><variable type=\"Number\" id=\"a\">a</variable></variables><block type=\"event_trigger\" deletable=\"false\" x=\"40\" y=\"40\"><field name=\"trigger\">no_ext_trigger</field><next><block type=\"entity_execute_command\"><value name=\"entity\"><block type=\"entity_from_deps\"></block></value><value name=\"command\"><block type=\"text\"><field name=\"TEXT\">particle minecraft:lava ~ ~1 ~</field></block></value><next><block type=\"controls_if\"><value name=\"IF0\"><block type=\"java_code_get\"><field name=\"CODE\">net.hackermdch.pgc.Timer.isDone(entity,\"zhuo_shao\")</field></block></value><statement name=\"DO0\"><block type=\"variables_set_number\"><mutation xmlns=\"http://www.w3.org/1999/xhtml\" is_player_var=\"false\" has_entity=\"false\"></mutation><field name=\"VAR\">local:a</field><value name=\"VAL\"><block type=\"entity_potioneffectlevel\"><field name=\"potion\">CUSTOM:Zhuoshao</field><value name=\"entity\"><block type=\"entity_from_deps\"></block></value></block></value><next><block type=\"deal_damage\"><value name=\"entity\"><block type=\"entity_from_deps\"></block></value><value name=\"amount\"><block type=\"math_dual_ops\" inline=\"false\"><field name=\"OP\">MAX</field><value name=\"A\"><block type=\"math_dual_ops\"><field name=\"OP\">MULTIPLY</field><value name=\"A\"><block type=\"variables_get_number\"><mutation xmlns=\"http://www.w3.org/1999/xhtml\" is_player_var=\"false\" has_entity=\"false\"></mutation><field name=\"VAR\">local:a</field></block></value><value name=\"B\"><block type=\"math_number\"><field name=\"NUM\">1</field></block></value></block></value><value name=\"B\"><block type=\"math_dual_ops\"><field name=\"OP\">MULTIPLY</field><value name=\"A\"><block type=\"entity_health\"><value name=\"entity\"><block type=\"entity_from_deps\"></block></value></block></value><value name=\"B\"><block type=\"math_dual_ops\"><field name=\"OP\">MULTIPLY</field><value name=\"A\"><block type=\"math_dual_ops\"><field name=\"OP\">ADD</field><value name=\"A\"><block type=\"variables_get_number\"><mutation xmlns=\"http://www.w3.org/1999/xhtml\" is_player_var=\"false\" has_entity=\"false\"></mutation><field name=\"VAR\">local:a</field></block></value><value name=\"B\"><block type=\"math_number\"><field name=\"NUM\">1</field></block></value></block></value><value name=\"B\"><block type=\"math_number\"><field name=\"NUM\">0.01</field></block></value></block></value></block></value></block></value><value name=\"damagesource\"><block type=\"damagesource_from_type\"><field name=\"damagetype\">LAVA</field></block></value><next><block type=\"java_code\"><field name=\"CODE\">net.hackermdch.pgc.Timer.set(entity,\"zhuo_shao\",40);</field></block></next></block></next></block></statement></block></next></block></next></block></xml>",
    "skipDependencyNullCheck": false
  }
}